langchain_desearch/__init__.py
langchain_desearch/agent.py
langchain_desearch/search_tools.py
langchain_desearch/tools.py
tests/__init__.py
langchain_desearch-1.0.6.dist-info/METADATA
langchain_desearch-1.0.6.dist-info/WHEEL
langchain_desearch-1.0.6.dist-info/top_level.txt
langchain_desearch-1.0.6.dist-info/RECORD
