Metadata-Version: 2.4
Name: langchain-desearch
Version: 1.0.6
Summary: LangChain integration with Desearch API for search and data-fetching tools.
Home-page: https://github.com/Desearch-ai/langchain-desearch
Author: Desearch
Author-email: Desearch <support@desearch.ai>
License: MIT
Project-URL: Homepage, https://github.com/Desearch-ai/langchain-desearch
Classifier: Programming Language :: Python :: 3
Classifier: License :: OSI Approved :: MIT License
Classifier: Operating System :: OS Independent
Requires-Python: >=3.7
Requires-Dist: langchain-core>=0.1.0
Requires-Dist: desearch-py>=1.0.0
Requires-Dist: langchain-deepseek>=0.1.0
Requires-Dist: python-dotenv>=0.21.0
Requires-Dist: pytest>=7.0.0
Dynamic: author
Dynamic: home-page
Dynamic: requires-python
